Metadata-Version: 2.1
Name: DARKI7X
Version: 29.0
Summary: For developers
Home-page: https://t.me/LegendsLIB
Author: Legends
Author-email: Alaaposhnaq@gmail.com
License: UNKNOWN
Project-URL: Bug Tracker, https://github.com/pypa/sampleproject/issues
Keywords: LegendsLIB
Platform: UNKNOWN
Classifier: Development Status :: 1 - Planning
Classifier: Intended Audience :: Developers
Classifier: Programming Language :: Python :: 3
Classifier: Operating System :: Unix
Classifier: Operating System :: MacOS :: MacOS X
Classifier: Operating System :: Microsoft :: Windows
License-File: LICENSE
